[
  {
    "ru": {
      "sentence": "– Здравствуйте!",
      "audio": "Приятного аппетита!=.translated.json.audio\\0.ogg",
      "spacy_tokens": [
        {
          "text": "–",
          "lemma": "–",
          "morph": "",
          "pos": "PUNCT"
        },
        {
          "text": "Здравствуйте",
          "lemma": "здравствовать",
          "morph": "Aspect=Imp|Mood=Imp|Number=Plur|Person=Second|VerbForm=Fin|Voice=Act",
          "pos": "VERB"
        },
        {
          "text": "!",
          "lemma": "!",
          "morph": "",
          "pos": "PUNCT"
        }
      ]
    },
    "en": {
      "sentence": "- Hello!"
    }
  },
  {
    "ru": {
      "sentence": "– Здравствуйте! Пожалуйста, вот меню",
      "audio": "Приятного аппетита!=.translated.json.audio\\1.ogg",
      "spacy_tokens": [
        {
          "text": "–",
          "lemma": "–",
          "morph": "",
          "pos": "PUNCT"
        },
        {
          "text": "Здравствуйте",
          "lemma": "здравствовать",
          "morph": "Aspect=Imp|Mood=Imp|Number=Plur|Person=Second|VerbForm=Fin|Voice=Act",
          "pos": "VERB"
        },
        {
          "text": "!",
          "lemma": "!",
          "morph": "",
          "pos": "PUNCT"
        },
        {
          "text": "Пожалуйста",
          "lemma": "пожалуйста",
          "morph": "Degree=Pos",
          "pos": "ADV"
        },
        {
          "text": ",",
          "lemma": ",",
          "morph": "",
          "pos": "PUNCT"
        },
        {
          "text": "вот",
          "lemma": "вот",
          "morph": "",
          "pos": "PART"
        },
        {
          "text": "меню",
          "lemma": "меню",
          "morph": "Animacy=Inan|Case=Nom|Gender=Neut|Number=Sing",
          "pos": "NOUN"
        }
      ]
    },
    "en": {
      "sentence": "- Hello! Please, here's the menu."
    }
  },
  {
    "ru": {
      "sentence": "– Спасибо.",
      "audio": "Приятного аппетита!=.translated.json.audio\\2.ogg",
      "spacy_tokens": [
        {
          "text": "–",
          "lemma": "–",
          "morph": "",
          "pos": "PUNCT"
        },
        {
          "text": "Спасибо",
          "lemma": "спасибо",
          "morph": "Animacy=Inan|Case=Nom|Gender=Neut|Number=Sing",
          "pos": "NOUN"
        },
        {
          "text": ".",
          "lemma": ".",
          "morph": "",
          "pos": "PUNCT"
        }
      ]
    },
    "en": {
      "sentence": "- Thank you."
    }
  },
  {
    "ru": {
      "sentence": "Так… Картофель, салат “Цезарь”, грибы, помидоры, огурцы, салат “Русский”, салат “Греческий”, салат картофельный, салат морковный… Извините, а у вас есть гуляш или ростбиф?",
      "audio": "Приятного аппетита!=.translated.json.audio\\3.ogg",
      "spacy_tokens": [
        {
          "text": "Так",
          "lemma": "так",
          "morph": "Degree=Pos",
          "pos": "ADV"
        },
        {
          "text": "…",
          "lemma": "…",
          "morph": "",
          "pos": "PUNCT"
        },
        {
          "text": "Картофель",
          "lemma": "картофель",
          "morph": "Animacy=Inan|Case=Nom|Gender=Masc|Number=Sing",
          "pos": "NOUN"
        },
        {
          "text": ",",
          "lemma": ",",
          "morph": "",
          "pos": "PUNCT"
        },
        {
          "text": "салат",
          "lemma": "салат",
          "morph": "Animacy=Inan|Case=Nom|Gender=Masc|Number=Sing",
          "pos": "NOUN"
        },
        {
          "text": "“",
          "lemma": "“",
          "morph": "",
          "pos": "PUNCT"
        },
        {
          "text": "Цезарь",
          "lemma": "цезарь",
          "morph": "Animacy=Inan|Case=Nom|Gender=Masc|Number=Sing",
          "pos": "NOUN"
        },
        {
          "text": "”",
          "lemma": "”",
          "morph": "",
          "pos": "PUNCT"
        },
        {
          "text": ",",
          "lemma": ",",
          "morph": "",
          "pos": "PUNCT"
        },
        {
          "text": "грибы",
          "lemma": "гриб",
          "morph": "Animacy=Inan|Case=Nom|Gender=Masc|Number=Plur",
          "pos": "NOUN"
        },
        {
          "text": ",",
          "lemma": ",",
          "morph": "",
          "pos": "PUNCT"
        },
        {
          "text": "помидоры",
          "lemma": "помидор",
          "morph": "Animacy=Inan|Case=Nom|Gender=Masc|Number=Plur",
          "pos": "NOUN"
        },
        {
          "text": ",",
          "lemma": ",",
          "morph": "",
          "pos": "PUNCT"
        },
        {
          "text": "огурцы",
          "lemma": "огурец",
          "morph": "Animacy=Inan|Case=Acc|Gender=Masc|Number=Plur",
          "pos": "NOUN"
        },
        {
          "text": ",",
          "lemma": ",",
          "morph": "",
          "pos": "PUNCT"
        },
        {
          "text": "салат",
          "lemma": "салат",
          "morph": "Animacy=Inan|Case=Nom|Gender=Masc|Number=Sing",
          "pos": "NOUN"
        },
        {
          "text": "“",
          "lemma": "“",
          "morph": "",
          "pos": "PUNCT"
        },
        {
          "text": "Русский",
          "lemma": "русский",
          "morph": "Case=Nom|Degree=Pos|Gender=Masc|Number=Sing",
          "pos": "ADJ"
        },
        {
          "text": "”",
          "lemma": "”",
          "morph": "",
          "pos": "PUNCT"
        },
        {
          "text": ",",
          "lemma": ",",
          "morph": "",
          "pos": "PUNCT"
        },
        {
          "text": "салат",
          "lemma": "салат",
          "morph": "Animacy=Inan|Case=Nom|Gender=Masc|Number=Sing",
          "pos": "NOUN"
        },
        {
          "text": "“",
          "lemma": "“",
          "morph": "",
          "pos": "PUNCT"
        },
        {
          "text": "Греческий",
          "lemma": "греческий",
          "morph": "Case=Nom|Degree=Pos|Gender=Masc|Number=Sing",
          "pos": "ADJ"
        },
        {
          "text": "”",
          "lemma": "”",
          "morph": "",
          "pos": "PUNCT"
        },
        {
          "text": ",",
          "lemma": ",",
          "morph": "",
          "pos": "PUNCT"
        },
        {
          "text": "салат",
          "lemma": "салат",
          "morph": "Animacy=Inan|Case=Nom|Gender=Masc|Number=Sing",
          "pos": "NOUN"
        },
        {
          "text": "картофельный",
          "lemma": "картофельный",
          "morph": "Case=Nom|Degree=Pos|Gender=Masc|Number=Sing",
          "pos": "ADJ"
        },
        {
          "text": ",",
          "lemma": ",",
          "morph": "",
          "pos": "PUNCT"
        },
        {
          "text": "салат",
          "lemma": "салат",
          "morph": "Animacy=Inan|Case=Nom|Gender=Masc|Number=Sing",
          "pos": "NOUN"
        },
        {
          "text": "морковный",
          "lemma": "морковный",
          "morph": "Case=Nom|Degree=Pos|Gender=Masc|Number=Sing",
          "pos": "ADJ"
        },
        {
          "text": "…",
          "lemma": "…",
          "morph": "",
          "pos": "PUNCT"
        },
        {
          "text": "Извините",
          "lemma": "извинить",
          "morph": "Aspect=Perf|Mood=Imp|Number=Plur|Person=Second|VerbForm=Fin|Voice=Act",
          "pos": "VERB"
        },
        {
          "text": ",",
          "lemma": ",",
          "morph": "",
          "pos": "PUNCT"
        },
        {
          "text": "а",
          "lemma": "а",
          "morph": "",
          "pos": "CCONJ"
        },
        {
          "text": "у",
          "lemma": "у",
          "morph": "",
          "pos": "ADP"
        },
        {
          "text": "вас",
          "lemma": "вас",
          "morph": "Case=Gen|Number=Plur|Person=Second",
          "pos": "PRON"
        },
        {
          "text": "есть",
          "lemma": "быть",
          "morph": "Aspect=Imp|Mood=Ind|Number=Sing|Person=Third|Tense=Pres|VerbForm=Fin|Voice=Act",
          "pos": "VERB"
        },
        {
          "text": "гуляш",
          "lemma": "гуляш",
          "morph": "Animacy=Inan|Case=Nom|Gender=Masc|Number=Sing",
          "pos": "NOUN"
        },
        {
          "text": "или",
          "lemma": "или",
          "morph": "",
          "pos": "CCONJ"
        },
        {
          "text": "ростбиф",
          "lemma": "ростбиф",
          "morph": "Animacy=Inan|Case=Nom|Gender=Masc|Number=Sing",
          "pos": "NOUN"
        },
        {
          "text": "?",
          "lemma": "?",
          "morph": "",
          "pos": "PUNCT"
        }
      ]
    },
    "en": {
      "sentence": "So... Potatoes, Caesar salad, mushrooms, tomatoes, cucumbers, Russian salad, Greek salad, potato salad, carrot salad... Excuse me, do you have goulash or roast beef?"
    }
  },
  {
    "ru": {
      "sentence": "Может быть, курица?",
      "audio": "Приятного аппетита!=.translated.json.audio\\4.ogg",
      "spacy_tokens": [
        {
          "text": "Может",
          "lemma": "мочь",
          "morph": "Aspect=Imp|Mood=Ind|Number=Sing|Person=Third|Tense=Pres|VerbForm=Fin|Voice=Act",
          "pos": "VERB"
        },
        {
          "text": "быть",
          "lemma": "быть",
          "morph": "Aspect=Imp|VerbForm=Inf|Voice=Act",
          "pos": "VERB"
        },
        {
          "text": ",",
          "lemma": ",",
          "morph": "",
          "pos": "PUNCT"
        },
        {
          "text": "курица",
          "lemma": "курица",
          "morph": "Animacy=Anim|Case=Nom|Gender=Fem|Number=Sing",
          "pos": "NOUN"
        },
        {
          "text": "?",
          "lemma": "?",
          "morph": "",
          "pos": "PUNCT"
        }
      ]
    },
    "en": {
      "sentence": "How about chicken?"
    }
  },
  {
    "ru": {
      "sentence": "– Нет, гуляша нет, ростбифа тоже нет.",
      "audio": "Приятного аппетита!=.translated.json.audio\\5.ogg",
      "spacy_tokens": [
        {
          "text": "–",
          "lemma": "–",
          "morph": "",
          "pos": "PUNCT"
        },
        {
          "text": "Нет",
          "lemma": "нет",
          "morph": "Polarity=Neg",
          "pos": "PART"
        },
        {
          "text": ",",
          "lemma": ",",
          "morph": "",
          "pos": "PUNCT"
        },
        {
          "text": "гуляша",
          "lemma": "гуляш",
          "morph": "Animacy=Inan|Case=Gen|Gender=Masc|Number=Sing",
          "pos": "NOUN"
        },
        {
          "text": "нет",
          "lemma": "нет",
          "morph": "Aspect=Imp|Mood=Ind|Number=Sing|Person=Third|Tense=Pres|VerbForm=Fin|Voice=Act",
          "pos": "VERB"
        },
        {
          "text": ",",
          "lemma": ",",
          "morph": "",
          "pos": "PUNCT"
        },
        {
          "text": "ростбифа",
          "lemma": "ростбиф",
          "morph": "Animacy=Inan|Case=Gen|Gender=Masc|Number=Sing",
          "pos": "NOUN"
        },
        {
          "text": "тоже",
          "lemma": "тоже",
          "morph": "Degree=Pos",
          "pos": "ADV"
        },
        {
          "text": "нет",
          "lemma": "нет",
          "morph": "Aspect=Imp|Mood=Ind|Number=Sing|Person=Third|Tense=Pres|VerbForm=Fin|Voice=Act",
          "pos": "VERB"
        },
        {
          "text": ".",
          "lemma": ".",
          "morph": "",
          "pos": "PUNCT"
        }
      ]
    },
    "en": {
      "sentence": "- No, no goulash, no roast beef."
    }
  },
  {
    "ru": {
      "sentence": "И курицы нет.",
      "audio": "Приятного аппетита!=.translated.json.audio\\6.ogg",
      "spacy_tokens": [
        {
          "text": "И",
          "lemma": "и",
          "morph": "",
          "pos": "CCONJ"
        },
        {
          "text": "курицы",
          "lemma": "курица",
          "morph": "Animacy=Anim|Case=Nom|Gender=Fem|Number=Plur",
          "pos": "NOUN"
        },
        {
          "text": "нет",
          "lemma": "нет",
          "morph": "Aspect=Imp|Mood=Ind|Number=Sing|Person=Third|Tense=Pres|VerbForm=Fin|Voice=Act",
          "pos": "VERB"
        },
        {
          "text": ".",
          "lemma": ".",
          "morph": "",
          "pos": "PUNCT"
        }
      ]
    },
    "en": {
      "sentence": "And no chicken."
    }
  },
  {
    "ru": {
      "sentence": "Вообще мяса у нас нет",
      "audio": "Приятного аппетита!=.translated.json.audio\\7.ogg",
      "spacy_tokens": [
        {
          "text": "Вообще",
          "lemma": "вообще",
          "morph": "Degree=Pos",
          "pos": "ADV"
        },
        {
          "text": "мяса",
          "lemma": "мясо",
          "morph": "Animacy=Inan|Case=Gen|Gender=Neut|Number=Sing",
          "pos": "NOUN"
        },
        {
          "text": "у",
          "lemma": "у",
          "morph": "",
          "pos": "ADP"
        },
        {
          "text": "нас",
          "lemma": "нас",
          "morph": "Case=Gen|Number=Plur|Person=First",
          "pos": "PRON"
        },
        {
          "text": "нет",
          "lemma": "нет",
          "morph": "Aspect=Imp|Mood=Ind|Number=Sing|Person=Third|Tense=Pres|VerbForm=Fin|Voice=Act",
          "pos": "VERB"
        }
      ]
    },
    "en": {
      "sentence": "No meat at all."
    }
  },
  {
    "ru": {
      "sentence": "– А рыба?",
      "audio": "Приятного аппетита!=.translated.json.audio\\8.ogg",
      "spacy_tokens": [
        {
          "text": "–",
          "lemma": "–",
          "morph": "",
          "pos": "PUNCT"
        },
        {
          "text": "А",
          "lemma": "а",
          "morph": "",
          "pos": "CCONJ"
        },
        {
          "text": "рыба",
          "lemma": "рыба",
          "morph": "Animacy=Anim|Case=Nom|Gender=Fem|Number=Sing",
          "pos": "NOUN"
        },
        {
          "text": "?",
          "lemma": "?",
          "morph": "",
          "pos": "PUNCT"
        }
      ]
    },
    "en": {
      "sentence": "- What about fish?"
    }
  },
  {
    "ru": {
      "sentence": "– Рыбы у нас тоже нет",
      "audio": "Приятного аппетита!=.translated.json.audio\\9.ogg",
      "spacy_tokens": [
        {
          "text": "–",
          "lemma": "–",
          "morph": "",
          "pos": "PUNCT"
        },
        {
          "text": "Рыбы",
          "lemma": "рыба",
          "morph": "Animacy=Anim|Case=Nom|Gender=Fem|Number=Plur",
          "pos": "NOUN"
        },
        {
          "text": "у",
          "lemma": "у",
          "morph": "",
          "pos": "ADP"
        },
        {
          "text": "нас",
          "lemma": "нас",
          "morph": "Case=Gen|Number=Plur|Person=First",
          "pos": "PRON"
        },
        {
          "text": "тоже",
          "lemma": "тоже",
          "morph": "Degree=Pos",
          "pos": "ADV"
        },
        {
          "text": "нет",
          "lemma": "нет",
          "morph": "Aspect=Imp|Mood=Ind|Number=Sing|Person=Third|Tense=Pres|VerbForm=Fin|Voice=Act",
          "pos": "VERB"
        }
      ]
    },
    "en": {
      "sentence": "- No fish either."
    }
  },
  {
    "ru": {
      "sentence": "– А икра есть?",
      "audio": "Приятного аппетита!=.translated.json.audio\\10.ogg",
      "spacy_tokens": [
        {
          "text": "–",
          "lemma": "–",
          "morph": "",
          "pos": "PUNCT"
        },
        {
          "text": "А",
          "lemma": "а",
          "morph": "",
          "pos": "CCONJ"
        },
        {
          "text": "икра",
          "lemma": "икра",
          "morph": "Animacy=Inan|Case=Nom|Gender=Fem|Number=Sing",
          "pos": "NOUN"
        },
        {
          "text": "есть",
          "lemma": "быть",
          "morph": "Aspect=Imp|Mood=Ind|Number=Sing|Person=Third|Tense=Pres|VerbForm=Fin|Voice=Act",
          "pos": "VERB"
        },
        {
          "text": "?",
          "lemma": "?",
          "morph": "",
          "pos": "PUNCT"
        }
      ]
    },
    "en": {
      "sentence": "- Do we have caviar?"
    }
  },
  {
    "ru": {
      "sentence": "– У нас нет икры",
      "audio": "Приятного аппетита!=.translated.json.audio\\11.ogg",
      "spacy_tokens": [
        {
          "text": "–",
          "lemma": "–",
          "morph": "",
          "pos": "PUNCT"
        },
        {
          "text": "У",
          "lemma": "у",
          "morph": "",
          "pos": "ADP"
        },
        {
          "text": "нас",
          "lemma": "нас",
          "morph": "Case=Gen|Number=Plur|Person=First",
          "pos": "PRON"
        },
        {
          "text": "нет",
          "lemma": "нет",
          "morph": "Aspect=Imp|Mood=Ind|Number=Sing|Person=Third|Tense=Pres|VerbForm=Fin|Voice=Act",
          "pos": "VERB"
        },
        {
          "text": "икры",
          "lemma": "икра",
          "morph": "Animacy=Inan|Case=Gen|Gender=Fem|Number=Sing",
          "pos": "NOUN"
        }
      ]
    },
    "en": {
      "sentence": "- We have no caviar."
    }
  },
  {
    "ru": {
      "sentence": "– Как?",
      "audio": "Приятного аппетита!=.translated.json.audio\\12.ogg",
      "spacy_tokens": [
        {
          "text": "–",
          "lemma": "–",
          "morph": "",
          "pos": "PUNCT"
        },
        {
          "text": "Как",
          "lemma": "как",
          "morph": "Degree=Pos",
          "pos": "ADV"
        },
        {
          "text": "?",
          "lemma": "?",
          "morph": "",
          "pos": "PUNCT"
        }
      ]
    },
    "en": {
      "sentence": "- How?"
    }
  },
  {
    "ru": {
      "sentence": "Почему у вас нет мяса, у вас нет рыбы, у вас нет икры?",
      "audio": "Приятного аппетита!=.translated.json.audio\\13.ogg",
      "spacy_tokens": [
        {
          "text": "Почему",
          "lemma": "почему",
          "morph": "Degree=Pos",
          "pos": "ADV"
        },
        {
          "text": "у",
          "lemma": "у",
          "morph": "",
          "pos": "ADP"
        },
        {
          "text": "вас",
          "lemma": "вас",
          "morph": "Case=Gen|Number=Plur|Person=Second",
          "pos": "PRON"
        },
        {
          "text": "нет",
          "lemma": "нет",
          "morph": "Aspect=Imp|Mood=Ind|Number=Sing|Person=Third|Tense=Pres|VerbForm=Fin|Voice=Act",
          "pos": "VERB"
        },
        {
          "text": "мяса",
          "lemma": "мясо",
          "morph": "Animacy=Inan|Case=Gen|Gender=Neut|Number=Sing",
          "pos": "NOUN"
        },
        {
          "text": ",",
          "lemma": ",",
          "morph": "",
          "pos": "PUNCT"
        },
        {
          "text": "у",
          "lemma": "у",
          "morph": "",
          "pos": "ADP"
        },
        {
          "text": "вас",
          "lemma": "вас",
          "morph": "Case=Gen|Number=Plur|Person=Second",
          "pos": "PRON"
        },
        {
          "text": "нет",
          "lemma": "нет",
          "morph": "Aspect=Imp|Mood=Ind|Number=Sing|Person=Third|Tense=Pres|VerbForm=Fin|Voice=Act",
          "pos": "VERB"
        },
        {
          "text": "рыбы",
          "lemma": "рыба",
          "morph": "Animacy=Anim|Case=Gen|Gender=Fem|Number=Sing",
          "pos": "NOUN"
        },
        {
          "text": ",",
          "lemma": ",",
          "morph": "",
          "pos": "PUNCT"
        },
        {
          "text": "у",
          "lemma": "у",
          "morph": "",
          "pos": "ADP"
        },
        {
          "text": "вас",
          "lemma": "вас",
          "morph": "Case=Gen|Number=Plur|Person=Second",
          "pos": "PRON"
        },
        {
          "text": "нет",
          "lemma": "нет",
          "morph": "Aspect=Imp|Mood=Ind|Number=Sing|Person=Third|Tense=Pres|VerbForm=Fin|Voice=Act",
          "pos": "VERB"
        },
        {
          "text": "икры",
          "lemma": "икра",
          "morph": "Animacy=Inan|Case=Gen|Gender=Fem|Number=Sing",
          "pos": "NOUN"
        },
        {
          "text": "?",
          "lemma": "?",
          "morph": "",
          "pos": "PUNCT"
        }
      ]
    },
    "en": {
      "sentence": "Why don't you have meat, you don't have fish, you don't have caviar?"
    }
  },
  {
    "ru": {
      "sentence": "Это ресторан или столовая?",
      "audio": "Приятного аппетита!=.translated.json.audio\\14.ogg",
      "spacy_tokens": [
        {
          "text": "Это",
          "lemma": "это",
          "morph": "Animacy=Inan|Case=Nom|Gender=Neut|Number=Sing",
          "pos": "PRON"
        },
        {
          "text": "ресторан",
          "lemma": "ресторан",
          "morph": "Animacy=Inan|Case=Nom|Gender=Masc|Number=Sing",
          "pos": "NOUN"
        },
        {
          "text": "или",
          "lemma": "или",
          "morph": "",
          "pos": "CCONJ"
        },
        {
          "text": "столовая",
          "lemma": "столовая",
          "morph": "Animacy=Inan|Case=Nom|Gender=Fem|Number=Sing",
          "pos": "NOUN"
        },
        {
          "text": "?",
          "lemma": "?",
          "morph": "",
          "pos": "PUNCT"
        }
      ]
    },
    "en": {
      "sentence": "Is this a restaurant or a canteen?"
    }
  },
  {
    "ru": {
      "sentence": "– Это ресторан.",
      "audio": "Приятного аппетита!=.translated.json.audio\\15.ogg",
      "spacy_tokens": [
        {
          "text": "–",
          "lemma": "–",
          "morph": "",
          "pos": "PUNCT"
        },
        {
          "text": "Это",
          "lemma": "это",
          "morph": "Animacy=Inan|Case=Nom|Gender=Neut|Number=Sing",
          "pos": "PRON"
        },
        {
          "text": "ресторан",
          "lemma": "ресторан",
          "morph": "Animacy=Inan|Case=Nom|Gender=Masc|Number=Sing",
          "pos": "NOUN"
        },
        {
          "text": ".",
          "lemma": ".",
          "morph": "",
          "pos": "PUNCT"
        }
      ]
    },
    "en": {
      "sentence": "- This is a restaurant."
    }
  },
  {
    "ru": {
      "sentence": "Вы знаете, как называется наш ресторан?",
      "audio": "Приятного аппетита!=.translated.json.audio\\16.ogg",
      "spacy_tokens": [
        {
          "text": "Вы",
          "lemma": "вы",
          "morph": "Case=Nom|Number=Plur|Person=Second",
          "pos": "PRON"
        },
        {
          "text": "знаете",
          "lemma": "знать",
          "morph": "Aspect=Imp|Mood=Ind|Number=Plur|Person=Second|Tense=Pres|VerbForm=Fin|Voice=Act",
          "pos": "VERB"
        },
        {
          "text": ",",
          "lemma": ",",
          "morph": "",
          "pos": "PUNCT"
        },
        {
          "text": "как",
          "lemma": "как",
          "morph": "Degree=Pos",
          "pos": "ADV"
        },
        {
          "text": "называется",
          "lemma": "называться",
          "morph": "Aspect=Imp|Mood=Ind|Number=Sing|Person=Third|Tense=Pres|VerbForm=Fin|Voice=Mid",
          "pos": "VERB"
        },
        {
          "text": "наш",
          "lemma": "наш",
          "morph": "Case=Nom|Gender=Masc|Number=Sing",
          "pos": "DET"
        },
        {
          "text": "ресторан",
          "lemma": "ресторан",
          "morph": "Animacy=Inan|Case=Nom|Gender=Masc|Number=Sing",
          "pos": "NOUN"
        },
        {
          "text": "?",
          "lemma": "?",
          "morph": "",
          "pos": "PUNCT"
        }
      ]
    },
    "en": {
      "sentence": "Do you know what our restaurant is called?"
    }
  },
  {
    "ru": {
      "sentence": "– Да, знаю.",
      "audio": "Приятного аппетита!=.translated.json.audio\\17.ogg",
      "spacy_tokens": [
        {
          "text": "–",
          "lemma": "–",
          "morph": "",
          "pos": "PUNCT"
        },
        {
          "text": "Да",
          "lemma": "да",
          "morph": "",
          "pos": "PART"
        },
        {
          "text": ",",
          "lemma": ",",
          "morph": "",
          "pos": "PUNCT"
        },
        {
          "text": "знаю",
          "lemma": "знать",
          "morph": "Aspect=Imp|Mood=Ind|Number=Sing|Person=First|Tense=Pres|VerbForm=Fin|Voice=Act",
          "pos": "VERB"
        },
        {
          "text": ".",
          "lemma": ".",
          "morph": "",
          "pos": "PUNCT"
        }
      ]
    },
    "en": {
      "sentence": "- Yes, I do."
    }
  },
  {
    "ru": {
      "sentence": "Ваш ресторан называется “Лев Толстой”.",
      "audio": "Приятного аппетита!=.translated.json.audio\\18.ogg",
      "spacy_tokens": [
        {
          "text": "Ваш",
          "lemma": "ваш",
          "morph": "Case=Nom|Gender=Masc|Number=Sing",
          "pos": "DET"
        },
        {
          "text": "ресторан",
          "lemma": "ресторан",
          "morph": "Animacy=Inan|Case=Nom|Gender=Masc|Number=Sing",
          "pos": "NOUN"
        },
        {
          "text": "называется",
          "lemma": "называться",
          "morph": "Aspect=Imp|Mood=Ind|Number=Sing|Person=Third|Tense=Pres|VerbForm=Fin|Voice=Mid",
          "pos": "VERB"
        },
        {
          "text": "“",
          "lemma": "“",
          "morph": "",
          "pos": "PUNCT"
        },
        {
          "text": "Лев",
          "lemma": "лев",
          "morph": "Animacy=Anim|Case=Nom|Gender=Masc|Number=Sing",
          "pos": "PROPN"
        },
        {
          "text": "Толстой",
          "lemma": "толстой",
          "morph": "Animacy=Anim|Case=Nom|Gender=Masc|Number=Sing",
          "pos": "PROPN"
        },
        {
          "text": "”",
          "lemma": "”",
          "morph": "",
          "pos": "PUNCT"
        },
        {
          "text": ".",
          "lemma": ".",
          "morph": "",
          "pos": "PUNCT"
        }
      ]
    },
    "en": {
      "sentence": "Your restaurant is called Leo Tolstoy."
    }
  },
  {
    "ru": {
      "sentence": "Это мой любимый русский писатель.",
      "audio": "Приятного аппетита!=.translated.json.audio\\19.ogg",
      "spacy_tokens": [
        {
          "text": "Это",
          "lemma": "это",
          "morph": "Animacy=Inan|Case=Nom|Gender=Neut|Number=Sing",
          "pos": "PRON"
        },
        {
          "text": "мой",
          "lemma": "мой",
          "morph": "Case=Nom|Gender=Masc|Number=Sing",
          "pos": "DET"
        },
        {
          "text": "любимый",
          "lemma": "любимый",
          "morph": "Case=Nom|Degree=Pos|Gender=Masc|Number=Sing",
          "pos": "ADJ"
        },
        {
          "text": "русский",
          "lemma": "русский",
          "morph": "Case=Nom|Degree=Pos|Gender=Masc|Number=Sing",
          "pos": "ADJ"
        },
        {
          "text": "писатель",
          "lemma": "писатель",
          "morph": "Animacy=Anim|Case=Nom|Gender=Masc|Number=Sing",
          "pos": "NOUN"
        },
        {
          "text": ".",
          "lemma": ".",
          "morph": "",
          "pos": "PUNCT"
        }
      ]
    },
    "en": {
      "sentence": "That's my favorite Russian writer."
    }
  },
  {
    "ru": {
      "sentence": "Поэтому я здесь",
      "audio": "Приятного аппетита!=.translated.json.audio\\20.ogg",
      "spacy_tokens": [
        {
          "text": "Поэтому",
          "lemma": "поэтому",
          "morph": "Degree=Pos",
          "pos": "ADV"
        },
        {
          "text": "я",
          "lemma": "я",
          "morph": "Case=Nom|Number=Sing|Person=First",
          "pos": "PRON"
        },
        {
          "text": "здесь",
          "lemma": "здесь",
          "morph": "Degree=Pos",
          "pos": "ADV"
        }
      ]
    },
    "en": {
      "sentence": "That's why I'm here."
    }
  },
  {
    "ru": {
      "sentence": "– А вы знаете, что Лев Толстой был вегетарианцем?",
      "audio": "Приятного аппетита!=.translated.json.audio\\21.ogg",
      "spacy_tokens": [
        {
          "text": "–",
          "lemma": "–",
          "morph": "",
          "pos": "PUNCT"
        },
        {
          "text": "А",
          "lemma": "а",
          "morph": "",
          "pos": "CCONJ"
        },
        {
          "text": "вы",
          "lemma": "вы",
          "morph": "Case=Nom|Number=Plur|Person=Second",
          "pos": "PRON"
        },
        {
          "text": "знаете",
          "lemma": "знать",
          "morph": "Aspect=Imp|Mood=Ind|Number=Plur|Person=Second|Tense=Pres|VerbForm=Fin|Voice=Act",
          "pos": "VERB"
        },
        {
          "text": ",",
          "lemma": ",",
          "morph": "",
          "pos": "PUNCT"
        },
        {
          "text": "что",
          "lemma": "что",
          "morph": "",
          "pos": "SCONJ"
        },
        {
          "text": "Лев",
          "lemma": "лев",
          "morph": "Animacy=Anim|Case=Nom|Gender=Masc|Number=Sing",
          "pos": "PROPN"
        },
        {
          "text": "Толстой",
          "lemma": "толстой",
          "morph": "Animacy=Anim|Case=Nom|Gender=Masc|Number=Sing",
          "pos": "PROPN"
        },
        {
          "text": "был",
          "lemma": "был",
          "morph": "Aspect=Imp|Gender=Masc|Mood=Ind|Number=Sing|Tense=Past|VerbForm=Fin|Voice=Act",
          "pos": "AUX"
        },
        {
          "text": "вегетарианцем",
          "lemma": "вегетарианец",
          "morph": "Animacy=Anim|Case=Ins|Gender=Masc|Number=Sing",
          "pos": "NOUN"
        },
        {
          "text": "?",
          "lemma": "?",
          "morph": "",
          "pos": "PUNCT"
        }
      ]
    },
    "en": {
      "sentence": "- Did you know that Leo Tolstoy was a vegetarian?"
    }
  },
  {
    "ru": {
      "sentence": "И ресторан наш тоже вегетарианский",
      "audio": "Приятного аппетита!=.translated.json.audio\\22.ogg",
      "spacy_tokens": [
        {
          "text": "И",
          "lemma": "и",
          "morph": "",
          "pos": "CCONJ"
        },
        {
          "text": "ресторан",
          "lemma": "ресторан",
          "morph": "Animacy=Inan|Case=Nom|Gender=Masc|Number=Sing",
          "pos": "NOUN"
        },
        {
          "text": "наш",
          "lemma": "наш",
          "morph": "Case=Nom|Gender=Masc|Number=Sing",
          "pos": "DET"
        },
        {
          "text": "тоже",
          "lemma": "тоже",
          "morph": "Degree=Pos",
          "pos": "ADV"
        },
        {
          "text": "вегетарианский",
          "lemma": "вегетарианский",
          "morph": "Case=Nom|Degree=Pos|Gender=Masc|Number=Sing",
          "pos": "ADJ"
        }
      ]
    },
    "en": {
      "sentence": "And our restaurant is also vegetarian."
    }
  },
  {
    "ru": {
      "sentence": "– А Пушкин?",
      "audio": "Приятного аппетита!=.translated.json.audio\\23.ogg",
      "spacy_tokens": [
        {
          "text": "–",
          "lemma": "–",
          "morph": "",
          "pos": "PUNCT"
        },
        {
          "text": "А",
          "lemma": "а",
          "morph": "",
          "pos": "CCONJ"
        },
        {
          "text": "Пушкин",
          "lemma": "пушкин",
          "morph": "Animacy=Anim|Case=Nom|Gender=Masc|Number=Sing",
          "pos": "PROPN"
        },
        {
          "text": "?",
          "lemma": "?",
          "morph": "",
          "pos": "PUNCT"
        }
      ]
    },
    "en": {
      "sentence": "- And Pushkin?"
    }
  },
  {
    "ru": {
      "sentence": "Он тоже был вегетарианцем?",
      "audio": "Приятного аппетита!=.translated.json.audio\\24.ogg",
      "spacy_tokens": [
        {
          "text": "Он",
          "lemma": "он",
          "morph": "Case=Nom|Gender=Masc|Number=Sing|Person=Third",
          "pos": "PRON"
        },
        {
          "text": "тоже",
          "lemma": "тоже",
          "morph": "Degree=Pos",
          "pos": "ADV"
        },
        {
          "text": "был",
          "lemma": "был",
          "morph": "Aspect=Imp|Gender=Masc|Mood=Ind|Number=Sing|Tense=Past|VerbForm=Fin|Voice=Act",
          "pos": "AUX"
        },
        {
          "text": "вегетарианцем",
          "lemma": "вегетарианец",
          "morph": "Animacy=Anim|Case=Ins|Gender=Masc|Number=Sing",
          "pos": "NOUN"
        },
        {
          "text": "?",
          "lemma": "?",
          "morph": "",
          "pos": "PUNCT"
        }
      ]
    },
    "en": {
      "sentence": "Was he a vegetarian too?"
    }
  },
  {
    "ru": {
      "sentence": "– Нет",
      "audio": "Приятного аппетита!=.translated.json.audio\\25.ogg",
      "spacy_tokens": [
        {
          "text": "–",
          "lemma": "–",
          "morph": "",
          "pos": "PUNCT"
        },
        {
          "text": "Нет",
          "lemma": "нет",
          "morph": "",
          "pos": "PART"
        }
      ]
    },
    "en": {
      "sentence": "- No, he wasn't."
    }
  },
  {
    "ru": {
      "sentence": "– Очень хорошо!",
      "audio": "Приятного аппетита!=.translated.json.audio\\26.ogg",
      "spacy_tokens": [
        {
          "text": "–",
          "lemma": "–",
          "morph": "",
          "pos": "PUNCT"
        },
        {
          "text": "Очень",
          "lemma": "очень",
          "morph": "Degree=Pos",
          "pos": "ADV"
        },
        {
          "text": "хорошо",
          "lemma": "хороший",
          "morph": "Degree=Pos|Gender=Neut|Number=Sing|StyleVariant=Short",
          "pos": "ADJ"
        },
        {
          "text": "!",
          "lemma": "!",
          "morph": "",
          "pos": "PUNCT"
        }
      ]
    },
    "en": {
      "sentence": "- Very good!"
    }
  },
  {
    "ru": {
      "sentence": "Ресторан “Пушкин ” рядом.",
      "audio": "Приятного аппетита!=.translated.json.audio\\27.ogg",
      "spacy_tokens": [
        {
          "text": "Ресторан",
          "lemma": "ресторан",
          "morph": "Animacy=Inan|Case=Nom|Gender=Masc|Number=Sing",
          "pos": "NOUN"
        },
        {
          "text": "“",
          "lemma": "“",
          "morph": "",
          "pos": "PUNCT"
        },
        {
          "text": "Пушкин",
          "lemma": "пушкин",
          "morph": "Animacy=Anim|Case=Nom|Gender=Masc|Number=Sing",
          "pos": "PROPN"
        },
        {
          "text": "”",
          "lemma": "”",
          "morph": "",
          "pos": "PUNCT"
        },
        {
          "text": "рядом",
          "lemma": "рядом",
          "morph": "Degree=Pos",
          "pos": "ADV"
        },
        {
          "text": ".",
          "lemma": ".",
          "morph": "",
          "pos": "PUNCT"
        }
      ]
    },
    "en": {
      "sentence": "Pushkin's restaurant is next door."
    }
  },
  {
    "ru": {
      "sentence": "И это мой любимый поэт.",
      "audio": "Приятного аппетита!=.translated.json.audio\\28.ogg",
      "spacy_tokens": [
        {
          "text": "И",
          "lemma": "и",
          "morph": "",
          "pos": "CCONJ"
        },
        {
          "text": "это",
          "lemma": "это",
          "morph": "Animacy=Inan|Case=Nom|Gender=Neut|Number=Sing",
          "pos": "PRON"
        },
        {
          "text": "мой",
          "lemma": "мой",
          "morph": "Case=Nom|Gender=Masc|Number=Sing",
          "pos": "DET"
        },
        {
          "text": "любимый",
          "lemma": "любимый",
          "morph": "Case=Nom|Degree=Pos|Gender=Masc|Number=Sing",
          "pos": "ADJ"
        },
        {
          "text": "поэт",
          "lemma": "поэт",
          "morph": "Animacy=Anim|Case=Nom|Gender=Masc|Number=Sing",
          "pos": "NOUN"
        },
        {
          "text": ".",
          "lemma": ".",
          "morph": "",
          "pos": "PUNCT"
        }
      ]
    },
    "en": {
      "sentence": "And it's my favorite poet."
    }
  },
  {
    "ru": {
      "sentence": "Я думаю, в этом ресторане хорошее вино и шампанское",
      "audio": "Приятного аппетита!=.translated.json.audio\\29.ogg",
      "spacy_tokens": [
        {
          "text": "Я",
          "lemma": "я",
          "morph": "Case=Nom|Number=Sing|Person=First",
          "pos": "PRON"
        },
        {
          "text": "думаю",
          "lemma": "думать",
          "morph": "Aspect=Imp|Mood=Ind|Number=Sing|Person=First|Tense=Pres|VerbForm=Fin|Voice=Act",
          "pos": "VERB"
        },
        {
          "text": ",",
          "lemma": ",",
          "morph": "",
          "pos": "PUNCT"
        },
        {
          "text": "в",
          "lemma": "в",
          "morph": "",
          "pos": "ADP"
        },
        {
          "text": "этом",
          "lemma": "этот",
          "morph": "Case=Loc|Gender=Masc|Number=Sing",
          "pos": "DET"
        },
        {
          "text": "ресторане",
          "lemma": "ресторан",
          "morph": "Animacy=Inan|Case=Loc|Gender=Masc|Number=Sing",
          "pos": "NOUN"
        },
        {
          "text": "хорошее",
          "lemma": "хороший",
          "morph": "Animacy=Inan|Case=Acc|Degree=Pos|Gender=Neut|Number=Sing",
          "pos": "ADJ"
        },
        {
          "text": "вино",
          "lemma": "вино",
          "morph": "Animacy=Inan|Case=Acc|Gender=Neut|Number=Sing",
          "pos": "NOUN"
        },
        {
          "text": "и",
          "lemma": "и",
          "morph": "",
          "pos": "CCONJ"
        },
        {
          "text": "шампанское",
          "lemma": "шампанское",
          "morph": "Animacy=Inan|Case=Acc|Gender=Neut|Number=Sing",
          "pos": "NOUN"
        }
      ]
    },
    "en": {
      "sentence": "I think this restaurant has good wine and champagne."
    }
  },
  {
    "ru": {
      "sentence": "– Почему вы так думаете?",
      "audio": "Приятного аппетита!=.translated.json.audio\\30.ogg",
      "spacy_tokens": [
        {
          "text": "–",
          "lemma": "–",
          "morph": "",
          "pos": "PUNCT"
        },
        {
          "text": "Почему",
          "lemma": "почему",
          "morph": "Degree=Pos",
          "pos": "ADV"
        },
        {
          "text": "вы",
          "lemma": "вы",
          "morph": "Case=Nom|Number=Plur|Person=Second",
          "pos": "PRON"
        },
        {
          "text": "так",
          "lemma": "так",
          "morph": "Degree=Pos",
          "pos": "ADV"
        },
        {
          "text": "думаете",
          "lemma": "думать",
          "morph": "Aspect=Imp|Mood=Ind|Number=Plur|Person=Second|Tense=Pres|VerbForm=Fin|Voice=Act",
          "pos": "VERB"
        },
        {
          "text": "?",
          "lemma": "?",
          "morph": "",
          "pos": "PUNCT"
        }
      ]
    },
    "en": {
      "sentence": "- Why do you think so?"
    }
  },
  {
    "ru": {
      "sentence": "– Пушкин любил хорошее вино и шампанское.",
      "audio": "Приятного аппетита!=.translated.json.audio\\31.ogg",
      "spacy_tokens": [
        {
          "text": "–",
          "lemma": "–",
          "morph": "",
          "pos": "PUNCT"
        },
        {
          "text": "Пушкин",
          "lemma": "пушкин",
          "morph": "Animacy=Anim|Case=Nom|Gender=Masc|Number=Sing",
          "pos": "PROPN"
        },
        {
          "text": "любил",
          "lemma": "любить",
          "morph": "Aspect=Imp|Gender=Masc|Mood=Ind|Number=Sing|Tense=Past|VerbForm=Fin|Voice=Act",
          "pos": "VERB"
        },
        {
          "text": "хорошее",
          "lemma": "хороший",
          "morph": "Animacy=Inan|Case=Acc|Degree=Pos|Gender=Neut|Number=Sing",
          "pos": "ADJ"
        },
        {
          "text": "вино",
          "lemma": "вино",
          "morph": "Animacy=Inan|Case=Acc|Gender=Neut|Number=Sing",
          "pos": "NOUN"
        },
        {
          "text": "и",
          "lemma": "и",
          "morph": "",
          "pos": "CCONJ"
        },
        {
          "text": "шампанское",
          "lemma": "шампанское",
          "morph": "Animacy=Inan|Case=Acc|Gender=Neut|Number=Sing",
          "pos": "NOUN"
        },
        {
          "text": ".",
          "lemma": ".",
          "morph": "",
          "pos": "PUNCT"
        }
      ]
    },
    "en": {
      "sentence": "- Pushkin loved good wine and champagne."
    }
  },
  {
    "ru": {
      "sentence": "Я знаю его стихи!",
      "audio": "Приятного аппетита!=.translated.json.audio\\32.ogg",
      "spacy_tokens": [
        {
          "text": "Я",
          "lemma": "я",
          "morph": "Case=Nom|Number=Sing|Person=First",
          "pos": "PRON"
        },
        {
          "text": "знаю",
          "lemma": "знать",
          "morph": "Aspect=Imp|Mood=Ind|Number=Sing|Person=First|Tense=Pres|VerbForm=Fin|Voice=Act",
          "pos": "VERB"
        },
        {
          "text": "его",
          "lemma": "его",
          "morph": "",
          "pos": "DET"
        },
        {
          "text": "стихи",
          "lemma": "стих",
          "morph": "Animacy=Inan|Case=Acc|Gender=Masc|Number=Plur",
          "pos": "NOUN"
        },
        {
          "text": "!",
          "lemma": "!",
          "morph": "",
          "pos": "PUNCT"
        }
      ]
    },
    "en": {
      "sentence": "I know his poetry!"
    }
  },
  {
    "ru": {
      "sentence": "До свидания!",
      "audio": "Приятного аппетита!=.translated.json.audio\\33.ogg",
      "spacy_tokens": [
        {
          "text": "До",
          "lemma": "до",
          "morph": "",
          "pos": "ADP"
        },
        {
          "text": "свидания",
          "lemma": "свидание",
          "morph": "Animacy=Inan|Case=Gen|Gender=Neut|Number=Sing",
          "pos": "NOUN"
        },
        {
          "text": "!",
          "lemma": "!",
          "morph": "",
          "pos": "PUNCT"
        }
      ]
    },
    "en": {
      "sentence": "Goodbye!"
    }
  },
  {
    "ru": {
      "sentence": "– До свидания!",
      "audio": "Приятного аппетита!=.translated.json.audio\\34.ogg",
      "spacy_tokens": [
        {
          "text": "–",
          "lemma": "–",
          "morph": "",
          "pos": "PUNCT"
        },
        {
          "text": "До",
          "lemma": "до",
          "morph": "",
          "pos": "ADP"
        },
        {
          "text": "свидания",
          "lemma": "свидание",
          "morph": "Animacy=Inan|Case=Gen|Gender=Neut|Number=Sing",
          "pos": "NOUN"
        },
        {
          "text": "!",
          "lemma": "!",
          "morph": "",
          "pos": "PUNCT"
        }
      ]
    },
    "en": {
      "sentence": "- Goodbye!"
    }
  },
  {
    "ru": {
      "sentence": "Приятного аппетита!",
      "audio": "Приятного аппетита!=.translated.json.audio\\35.ogg",
      "spacy_tokens": [
        {
          "text": "Приятного",
          "lemma": "приятный",
          "morph": "Case=Gen|Degree=Pos|Gender=Masc|Number=Sing",
          "pos": "ADJ"
        },
        {
          "text": "аппетита",
          "lemma": "аппетит",
          "morph": "Animacy=Inan|Case=Gen|Gender=Masc|Number=Sing",
          "pos": "NOUN"
        },
        {
          "text": "!",
          "lemma": "!",
          "morph": "",
          "pos": "PUNCT"
        }
      ]
    },
    "en": {
      "sentence": "Bon appetit!"
    }
  }
]